drfkwargs/__init__.py
drfkwargs/class_based.py
drfkwargs/kwargs.py
drfkwargs-1.0.0.dist-info/LICENSE
drfkwargs-1.0.0.dist-info/METADATA
drfkwargs-1.0.0.dist-info/WHEEL
drfkwargs-1.0.0.dist-info/top_level.txt
drfkwargs-1.0.0.dist-info/RECORD
