Metadata-Version: 2.2
Name: drfkwargs
Version: 1.0.0
Summary: Django REST framework keywords names for extra_keyword meta attribute of serializers stored as constants
Author: DouleLove
License: MIT License
Project-URL: Repository, https://github.com/DouleLove/drfkwargs
Project-URL: Issues, https://github.com/DouleLove/drfkwargs/issues
Classifier: Development Status :: 5 - Production/Stable
Classifier: Intended Audience :: Developers
Classifier: Topic :: Utilities
Classifier: Natural Language :: English
Classifier: Operating System :: OS Independent
Classifier: License :: OSI Approved :: MIT License
Classifier: Programming Language :: Python :: 3
License-File: LICENSE
